lockfile_diff/__init__.py
lockfile_diff/__main__.py
lockfile_diff/base.py
lockfile_diff/errors.py
lockfile_diff/parser.py
lockfile_diff/registries.py
lockfile_diff/types.py
lockfile_diff/formats/__init__.py
lockfile_diff/formats/blocks.py
lockfile_diff/formats/json.py
lockfile_diff/formats/text.py
lockfile_diff/formats/toml.py
lockfile_diff/formats/yaml.py
lockfile_diff/schemas/__init__.py
lockfile_diff/schemas/autodetect.py
lockfile_diff/schemas/coursier.py
lockfile_diff/schemas/pants.py
lockfile_diff/schemas/pex.py
lockfile_diff/schemas/pex_info.py
lockfile_diff/util/__init__.py
lockfile_diff/util/io/__init__.py
lockfile_diff/util/io/rewind.py
lockfile_diff-0.3.4.dist-info/METADATA
lockfile_diff-0.3.4.dist-info/WHEEL
lockfile_diff-0.3.4.dist-info/entry_points.txt
lockfile_diff-0.3.4.dist-info/namespace_packages.txt
lockfile_diff-0.3.4.dist-info/top_level.txt
lockfile_diff-0.3.4.dist-info/RECORD
